pygltflib/__init__.py
pygltflib-1.0.dist-info/DESCRIPTION.rst
pygltflib-1.0.dist-info/METADATA
pygltflib-1.0.dist-info/RECORD
pygltflib-1.0.dist-info/WHEEL
pygltflib-1.0.dist-info/metadata.json
pygltflib-1.0.dist-info/top_level.txt
