Metadata-Version: 2.0
Name: pygltflib
Version: 1.0
Summary: Python library for reading, writing and managing 3D objects in the Khronos Group gltf and gltf2 formats. Python 3.6+
Home-page: https://gitlab.com/dodgyville/pygltflib
Author: Luke Miller
Author-email: dodgyville@gmail.com
License: UNKNOWN
Platform: UNKNOWN
Classifier: Programming Language :: Python :: 3
Classifier: License :: OSI Approved :: MIT License
Classifier: Operating System :: OS Independent
